{
  "unversionedId": "Cart/DeleteCart",
  "id": "Cart/DeleteCart",
  "title": "Delete a cart",
  "description": "This reference shows that this API will not delete the cart from the database, but shows that if you successfully send data, it will return you the fake deleted cart.",
  "source": "@site/docs/Cart/DeleteCart.md",
  "sourceDirName": "Cart",
  "slug": "/Cart/DeleteCart",
  "permalink": "/docs/Cart/DeleteCart",
  "draft": false,
  "editUrl": "https://github.com/facebook/docusaurus/tree/main/packages/create-docusaurus/templates/shared/docs/Cart/DeleteCart.md",
  "tags": [],
  "version": "current",
  "sidebarPosition": 9,
  "frontMatter": {
    "sidebar_position": 9
  },
  "sidebar": "tutorialSidebar",
  "previous": {
    "title": "Update a cart",
    "permalink": "/docs/Cart/UpdateCart"
  },
  "next": {
    "title": "User",
    "permalink": "/docs/category/user"
  }
}